openwisp_firmware_upgrader/__init__.py
openwisp_firmware_upgrader/admin.py
openwisp_firmware_upgrader/apps.py
openwisp_firmware_upgrader/exceptions.py
openwisp_firmware_upgrader/filters.py
openwisp_firmware_upgrader/hardware.py
openwisp_firmware_upgrader/models.py
openwisp_firmware_upgrader/settings.py
openwisp_firmware_upgrader/swapper.py
openwisp_firmware_upgrader/tasks.py
openwisp_firmware_upgrader/urls.py
openwisp_firmware_upgrader/utils.py
openwisp_firmware_upgrader/widgets.py
openwisp_firmware_upgrader/api/__init__.py
openwisp_firmware_upgrader/api/filters.py
openwisp_firmware_upgrader/api/serializers.py
openwisp_firmware_upgrader/api/urls.py
openwisp_firmware_upgrader/api/views.py
openwisp_firmware_upgrader/base/__init__.py
openwisp_firmware_upgrader/base/models.py
openwisp_firmware_upgrader/migrations/0001_initial.py
openwisp_firmware_upgrader/migrations/0002_default_permissions.py
openwisp_firmware_upgrader/migrations/0003_private_media.py
openwisp_firmware_upgrader/migrations/0004_batch_upgrade_operation_idle_status.py
openwisp_firmware_upgrader/migrations/0005_build_os_identifier.py
openwisp_firmware_upgrader/migrations/0006_create_device_firmware.py
openwisp_firmware_upgrader/migrations/0007_nullable_upgrade_operation_image.py
openwisp_firmware_upgrader/migrations/0008_firmware_image_baseurl.py
openwisp_firmware_upgrader/migrations/0009_upgrade_options.py
openwisp_firmware_upgrader/migrations/0010_alter_firmwareimage_file.py
openwisp_firmware_upgrader/migrations/0011_alter_category_organization.py
openwisp_firmware_upgrader/migrations/0012_update_image_type_identifiers.py
openwisp_firmware_upgrader/migrations/__init__.py
openwisp_firmware_upgrader/private_storage/__init__.py
openwisp_firmware_upgrader/private_storage/storage.py
openwisp_firmware_upgrader/private_storage/urls.py
openwisp_firmware_upgrader/private_storage/views.py
openwisp_firmware_upgrader/static/firmware-upgrader/css/device-firmware.css
openwisp_firmware_upgrader-1.2.1.dist-info/licenses/LICENSE
openwisp_firmware_upgrader-1.2.1.dist-info/METADATA
openwisp_firmware_upgrader-1.2.1.dist-info/WHEEL
openwisp_firmware_upgrader-1.2.1.dist-info/top_level.txt
openwisp_firmware_upgrader-1.2.1.dist-info/RECORD
