Metadata-Version: 2.4
Name: openwisp-firmware-upgrader
Version: 1.2.1
Summary: Firmware upgrader module of OpenWISP
Home-page: http://openwisp.org
Download-URL: https://github.com/openwisp/openwisp-firmware-upgrader/releases
Author: OpenWISP
Author-email: support@openwisp.io
License: GPL3
Keywords: django,netjson,networking,openwisp,firmware
Platform: Platform Independent
Classifier: Development Status :: 5 - Production/Stable
Classifier: Environment :: Web Environment
Classifier: Topic :: Internet :: WWW/HTTP
Classifier: Topic :: System :: Networking
Classifier: Intended Audience :: Developers
Classifier: License :: OSI Approved :: GNU General Public License v3 (GPLv3)
Classifier: Operating System :: OS Independent
Classifier: Framework :: Django
Classifier: Programming Language :: Python :: 3
License-File: LICENSE
Requires-Dist: openwisp-controller~=1.2.0
Requires-Dist: django-private-storage~=3.1.0
Dynamic: author
Dynamic: author-email
Dynamic: classifier
Dynamic: description
Dynamic: download-url
Dynamic: home-page
Dynamic: keywords
Dynamic: license
Dynamic: license-file
Dynamic: platform
Dynamic: requires-dist
Dynamic: summary
